gnsocket/__init__.py
gnsocket/exceptions.py
gnsocket/gn_socket.py
gnsocket/interface.py
gnsocket/library.py
gnsocket/server.py
gnsocket/socket_base.py
gnsocket/socket_client.py
gnsocket/socket_server.py
gnsocket-0.9.2.dist-info/LICENSE
gnsocket-0.9.2.dist-info/METADATA
gnsocket-0.9.2.dist-info/WHEEL
gnsocket-0.9.2.dist-info/top_level.txt
gnsocket-0.9.2.dist-info/RECORD
