Metadata-Version: 2.1
Name: gnsocket
Version: 0.9.2
Summary: GPS Network Socket, with asyncio stream manager
Home-page: https://gitlab.com/pineiden/gus
Author: David Pineda Osorio
Author-email: dpineda@csn.uchile.cl
License: GPL3
Platform: UNKNOWN
